ezids/__init__.py
ezids/gui.py
ezids/ids_core.py
ezids/main.py
ezids/resources/back.svg
ezids/resources/bookmark.svg
ezids/resources/clock.svg
ezids/resources/down.svg
ezids/resources/eye-off.svg
ezids/resources/eye.svg
ezids/resources/file-plus.svg
ezids/resources/folder.svg
ezids/resources/init.svg
ezids/resources/log.svg
ezids/resources/minus.svg
ezids/resources/pencil.svg
ezids/resources/play.svg
ezids/resources/plus.svg
ezids/resources/save.svg
ezids/resources/settings.svg
ezids/resources/slash.svg
ezids/resources/stop.svg
ezids/resources/zap.svg
ezids-1.0.1.dist-info/METADATA
ezids-1.0.1.dist-info/WHEEL
ezids-1.0.1.dist-info/entry_points.txt
ezids-1.0.1.dist-info/top_level.txt
ezids-1.0.1.dist-info/RECORD
