Metadata-Version: 2.4
Name: ezids
Version: 1.0.1
Summary: A simple host-based intrusion detection system with a PyQt GUI.
Author: Nolan Coe
Requires-Dist: PyQt6
Dynamic: author
Dynamic: description
Dynamic: description-content-type
Dynamic: requires-dist
Dynamic: summary
